jupyterlab_vim/__init__.py
jupyterlab_vim/_version.py
jupyterlab_vim-4.1.2.data/data/share/jupyter/labextensions/@axlair/jupyterlab_vim/package.json
jupyterlab_vim-4.1.2.data/data/share/jupyter/labextensions/@axlair/jupyterlab_vim/schemas/@axlair/jupyterlab_vim/package.json.orig
jupyterlab_vim-4.1.2.data/data/share/jupyter/labextensions/@axlair/jupyterlab_vim/schemas/@axlair/jupyterlab_vim/plugin.json
jupyterlab_vim-4.1.2.data/data/share/jupyter/labextensions/@axlair/jupyterlab_vim/static/252.e0500116419ca3a355d1.js
jupyterlab_vim-4.1.2.data/data/share/jupyter/labextensions/@axlair/jupyterlab_vim/static/353.26e59acf062beca638da.js
jupyterlab_vim-4.1.2.data/data/share/jupyter/labextensions/@axlair/jupyterlab_vim/static/747.a573445024188eae7034.js
jupyterlab_vim-4.1.2.data/data/share/jupyter/labextensions/@axlair/jupyterlab_vim/static/remoteEntry.18c80ddb6c2fb5e46397.js
jupyterlab_vim-4.1.2.data/data/share/jupyter/labextensions/@axlair/jupyterlab_vim/static/style.js
jupyterlab_vim-4.1.2.data/data/share/jupyter/labextensions/@axlair/jupyterlab_vim/static/third-party-licenses.json
jupyterlab_vim-4.1.2.data/data/share/jupyter/labextensions/@axlair/jupyterlab_vim/install.json
jupyterlab_vim-4.1.2.dist-info/METADATA
jupyterlab_vim-4.1.2.dist-info/WHEEL
jupyterlab_vim-4.1.2.dist-info/licenses/LICENSE
jupyterlab_vim-4.1.2.dist-info/RECORD
