Metadata-Version: 2.1
Name: jupyterlab-vim
Version: 4.1.2
Summary: Code cell vim bindings
Project-URL: Homepage, https://github.com/jupyterlab-contrib/jupyterlab-vim
Project-URL: Bug Tracker, https://github.com/jupyterlab-contrib/jupyterlab-vim/issues
Project-URL: Repository, https://github.com/jupyterlab-contrib/jupyterlab-vim.git
Author: Axel Fahy
License: MIT License
License-File: LICENSE
Classifier: Framework :: Jupyter
Classifier: Framework :: Jupyter :: JupyterLab
Classifier: Framework :: Jupyter :: JupyterLab :: 4
Classifier: Framework :: Jupyter :: JupyterLab :: Extensions
Classifier: Framework :: Jupyter :: JupyterLab :: Extensions :: Prebuilt
Classifier: License :: OSI Approved :: MIT License
Classifier: Programming Language :: Python
Classifier: Programming Language :: Python :: 3
Classifier: Programming Language :: Python :: 3.8
Classifier: Programming Language :: Python :: 3.9
Classifier: Programming Language :: Python :: 3.10
Classifier: Programming Language :: Python :: 3.11
Requires-Python: >=3.8
Requires-Dist: jupyterlab<5,>=4.1.0
